<pkg-contents spec="1.12"><f n="Palourde.app" o="root" g="admin" p="16877" pt="/Users/mlecarme/Developpement/Cocoa/palourde/Palourde/build/Release/Palourde.app" m="true" t="file"><f n="Contents" o="root" g="admin" p="16877"><f n="Frameworks" o="root" g="admin" p="16893"><f n="Growl.framework" o="root" g="admin" p="16893"><f n="Growl" o="root" g="admin" p="41469"><mod>mode</mod></f><f n="Headers" o="root" g="admin" p="41469"><f n="Growl.h" o="root" g="admin" p="33204"><mod>mode</mod></f><f n="GrowlApplicationBridge-Carbon.h" o="root" g="admin" p="33204"><mod>mode</mod></f><f n="GrowlApplicationBridge.h" o="root" g="admin" p="33204"><mod>mode</mod></f><f n="GrowlDefines.h" o="root" g="admin" p="33204"><mod>mode</mod></f><mod>mode</mod></f><f n="Resources" o="root" g="admin" p="41469"><f n="Info.plist" o="root" g="admin" p="33204"><mod>mode</mod></f><mod>mode</mod></f><f n="Versions" o="root" g="admin" p="16893"><f n="A" o="root" g="admin" p="16893"><f n="Growl" o="root" g="admin" p="33277"><mod>mode</mod></f><f n="Headers" o="root" g="admin" p="16893"><f n="Growl.h" o="root" g="admin" p="33204"><mod>mode</mod></f><f n="GrowlApplicationBridge-Carbon.h" o="root" g="admin" p="33204"><mod>mode</mod></f><f n="GrowlApplicationBridge.h" o="root" g="admin" p="33204"><mod>mode</mod></f><f n="GrowlDefines.h" o="root" g="admin" p="33204"><mod>mode</mod></f><mod>mode</mod></f><f n="Resources" o="root" g="admin" p="16893"><f n="Info.plist" o="root" g="admin" p="33204"><mod>mode</mod></f><mod>mode</mod></f><mod>mode</mod></f><f n="Current" o="root" g="admin" p="41469"><f n="Growl" o="root" g="admin" p="33277"><mod>mode</mod></f><f n="Headers" o="root" g="admin" p="16893"><f n="Growl.h" o="root" g="admin" p="33204"><mod>mode</mod></f><f n="GrowlApplicationBridge-Carbon.h" o="root" g="admin" p="33204"><mod>mode</mod></f><f n="GrowlApplicationBridge.h" o="root" g="admin" p="33204"><mod>mode</mod></f><f n="GrowlDefines.h" o="root" g="admin" p="33204"><mod>mode</mod></f><mod>mode</mod></f><f n="Resources" o="root" g="admin" p="16893"><f n="Info.plist" o="root" g="admin" p="33204"><mod>mode</mod></f><mod>mode</mod></f><mod>mode</mod></f><mod>mode</mod></f><mod>mode</mod></f><mod>mode</mod></f><f n="Info.plist" o="root" g="admin" p="33204"><mod>mode</mod></f><f n="MacOS" o="root" g="admin" p="16893"><f n="Palourde" o="root" g="admin" p="33277"><mod>mode</mod></f><mod>mode</mod></f><f n="PkgInfo" o="root" g="admin" p="33204"><mod>mode</mod></f><f n="Resources" o="root" g="admin" p="16877"><f n="bin" o="root" g="admin" p="16877"><f n="clamav-config" o="root" g="admin" p="33261"/><f n="clamconf" o="root" g="admin" p="33261"/><f n="clamdscan" o="root" g="admin" p="33261"/><f n="clamscan" o="root" g="admin" p="33261"/><f n="freshclam" o="root" g="admin" p="33261"/><f n="sigtool" o="root" g="admin" p="33261"/></f><f n="bombe.png" o="root" g="admin" p="33204"><mod>mode</mod></f><f n="bombe__s01.png" o="root" g="admin" p="33204"><mod>mode</mod></f><f n="bombe__s02.png" o="root" g="admin" p="33204"><mod>mode</mod></f><f n="bombe__s03.png" o="root" g="admin" p="33204"><mod>mode</mod></f><f n="bombe__s04.png" o="root" g="admin" p="33204"><mod>mode</mod></f><f n="English.lproj" o="root" g="admin" p="16893"><f n="InfoPlist.strings" o="root" g="admin" p="33204"><mod>mode</mod></f><f n="Localizable.strings" o="root" g="admin" p="33204"><mod>mode</mod></f><f n="MainMenu.nib" o="root" g="admin" p="33204"><mod>mode</mod></f><mod>mode</mod></f><f n="es.lproj" o="root" g="admin" p="16893"><f n="MainMenu.nib" o="root" g="admin" p="33204"><mod>mode</mod></f><mod>mode</mod></f><f n="French.lproj" o="root" g="admin" p="16893"><f n="Localizable.strings" o="root" g="admin" p="33204"><mod>mode</mod></f><f n="MainMenu.nib" o="root" g="admin" p="33204"><mod>mode</mod></f><mod>mode</mod></f><f n="include" o="root" g="admin" p="16877"><f n="clamav.h" o="root" g="admin" p="33188"/></f><f n="lapalourde.jpg" o="root" g="admin" p="33204"><mod>mode</mod></f><f n="lib" o="root" g="admin" p="16877"><f n="libclamav.5.dylib" o="root" g="admin" p="33261"/><f n="libclamav.a" o="root" g="admin" p="33188"/><f n="libclamav.dylib" o="root" g="admin" p="33261"/><f n="libclamav.la" o="root" g="admin" p="33261"/><f n="libclamunrar.5.dylib" o="root" g="admin" p="33261"/><f n="libclamunrar.a" o="root" g="admin" p="33188"/><f n="libclamunrar.dylib" o="root" g="admin" p="33261"/><f n="libclamunrar.la" o="root" g="admin" p="33261"/><f n="libclamunrar_iface.5.dylib" o="root" g="admin" p="33261"/><f n="libclamunrar_iface.a" o="root" g="admin" p="33188"/><f n="libclamunrar_iface.dylib" o="root" g="admin" p="33261"/><f n="libclamunrar_iface.la" o="root" g="admin" p="33261"/><f n="pkgconfig" o="root" g="admin" p="16877"><f n="libclamav.pc" o="root" g="admin" p="33188"/></f></f><f n="pl.lproj" o="root" g="admin" p="16893"><f n="MainMenu.nib" o="root" g="admin" p="33204"><mod>mode</mod></f><mod>mode</mod></f><f n="sbin" o="root" g="admin" p="16877"><f n="clamd" o="root" g="admin" p="33261"/></f><f n="Sneeze.wav" o="root" g="admin" p="33204"><mod>mode</mod></f><f n="UKKQueue Readme.txt" o="root" g="admin" p="33204"><mod>mode</mod></f></f></f><mod>group</mod></f></pkg-contents>